anpan/__init__.py
anpan/cli.py
anpan-0.1.1.dist-info/METADATA
anpan-0.1.1.dist-info/WHEEL
anpan-0.1.1.dist-info/top_level.txt
anpan-0.1.1.dist-info/RECORD
